hiplot/__init__.py
hiplot/__main__.py
hiplot/compress.py
hiplot/experiment.py
hiplot/fetchers.py
hiplot/fetchers_demo.py
hiplot/ipython.py
hiplot/pkginfo.py
hiplot/py.typed
hiplot/render.py
hiplot/server.py
hiplot/streamlit_helpers.py
hiplot/test_experiment.py
hiplot/test_fetchers.py
hiplot/test_render.py
hiplot/static/icon-w.svg
hiplot/static/icon.png
hiplot/static/icon.svg
hiplot/static/logo-w.svg
hiplot/static/logo.png
hiplot/static/logo.svg
hiplot/static/thumbnail.png
hiplot/static/built/hiplot.bundle.js
hiplot/static/built/streamlit_component/hiplot_streamlit.bundle.js
hiplot/static/built/streamlit_component/index.html
hiplot/templates/index.html
hiplot-0.1.33.dist-info/LICENSE
hiplot-0.1.33.dist-info/METADATA
hiplot-0.1.33.dist-info/NOTICE
hiplot-0.1.33.dist-info/WHEEL
hiplot-0.1.33.dist-info/entry_points.txt
hiplot-0.1.33.dist-info/top_level.txt
hiplot-0.1.33.dist-info/RECORD
