Metadata-Version: 2.1
Name: hiplot
Version: 0.1.33
Summary: High dimensional Interactive Plotting tool
Home-page: https://github.com/facebookresearch/hiplot
Author: Facebook AI Research
License: UNKNOWN
Platform: UNKNOWN
Requires-Python: >=3.6
Provides-Extra: dev
